mcp_db_filesystem/__init__.py
mcp_db_filesystem/__main__.py
mcp_db_filesystem/config.py
mcp_db_filesystem/database.py
mcp_db_filesystem/filesystem.py
mcp_db_filesystem/mysql.py
mcp_db_filesystem/redis_manager.py
mcp_db_filesystem/server.py
mcp_db_filesystem-1.1.4.dist-info/METADATA
mcp_db_filesystem-1.1.4.dist-info/WHEEL
mcp_db_filesystem-1.1.4.dist-info/entry_points.txt
mcp_db_filesystem-1.1.4.dist-info/licenses/LICENSE
mcp_db_filesystem-1.1.4.dist-info/RECORD
