Metadata-Version: 2.4
Name: mcp-db-filesystem
Version: 1.1.4
Summary: Simple and efficient MCP server for multi-database (SQL Server, MySQL) and Redis access with filesystem operations
Project-URL: Homepage, https://github.com/ppengit/mcp-db-filesystem
Project-URL: Repository, https://github.com/ppengit/mcp-db-filesystem
Project-URL: Issues, https://github.com/ppengit/mcp-db-filesystem/issues
Author-email: PJ <peng.it@qq.com>
License: MIT
License-File: LICENSE
Keywords: cross-platform,database,filesystem,mcp,mysql,redis,server,sqlserver
Classifier: Development Status :: 5 - Production/Stable
Classifier: Intended Audience :: Developers
Classifier: License :: OSI Approved :: MIT License
Classifier: Operating System :: OS Independent
Classifier: Programming Language :: Python :: 3
Classifier: Programming Language :: Python :: 3.11
Classifier: Programming Language :: Python :: 3.12
Classifier: Topic :: Database
Classifier: Topic :: Software Development :: Libraries :: Python Modules
Classifier: Topic :: System :: Filesystems
Requires-Python: >=3.11
Requires-Dist: aiofiles>=23.0.0
Requires-Dist: mcp>=1.9.3
Requires-Dist: pydantic>=2.0.0
Requires-Dist: pymysql>=1.1.0
Requires-Dist: pyodbc>=5.0.0
Requires-Dist: python-dotenv>=1.0.0
Requires-Dist: redis>=5.0.0
Requires-Dist: sqlalchemy>=2.0.0
Provides-Extra: dev
Requires-Dist: black>=23.0.0; extra == 'dev'
Requires-Dist: flake8>=6.0.0; extra == 'dev'
Requires-Dist: isort>=5.12.0; extra == 'dev'
Requires-Dist: mypy>=1.0.0; extra == 'dev'
Requires-Dist: pytest-asyncio>=0.21.0; extra == 'dev'
Requires-Dist: pytest-cov>=4.0.0; extra == 'dev'
Requires-Dist: pytest>=7.0.0; extra == 'dev'
Requires-Dist: twine>=6.1.0; extra == 'dev'
